jamdist/__init__.py
jamdist/distribution/__init__.py
jamdist/distribution/img_flower.py
jamdist/sampling/__init__.py
jamdist/sampling/esh.py
jamdist/sampling/hmc.py
jamdist/sampling/langevin.py
jam_dist-0.0.3.dist-info/METADATA
jam_dist-0.0.3.dist-info/WHEEL
jam_dist-0.0.3.dist-info/top_level.txt
jam_dist-0.0.3.dist-info/RECORD
