Metadata-Version: 2.1
Name: jam-dist
Version: 0.0.3
Summary: Distribution Research Toolbox
Home-page: https://github.com/qsh-zh/jam-dist
Author: Qsh.zh
Author-email: Qsh.zh27@gmail.com
License: MIT
Keywords: artificial intelligence,deep learning,sampling
Platform: UNKNOWN
Classifier: Development Status :: 4 - Beta
Classifier: Intended Audience :: Developers
Classifier: Topic :: Scientific/Engineering :: Artificial Intelligence
Classifier: License :: OSI Approved :: MIT License
Requires-Dist: einops (>=0.3)
Requires-Dist: torch (>=1.6)
Requires-Dist: gdown (>=4.2.0)
